crdb_dump/__init__.py
crdb_dump/cli.py
crdb_dump/export/data.py
crdb_dump/export/schema.py
crdb_dump/loader/loader.py
crdb_dump/utils/common.py
crdb_dump/utils/db_connection.py
crdb_dump/utils/io.py
crdb_dump/utils/logging.py
crdb_dump/utils/s3.py
crdb_dump/utils/type_constants.py
crdb_dump/verify/checksum.py
crdb_dump/verify/diff_utils.py
crdb_dump-0.3.0.dist-info/licenses/LICENSE
tests/test_integration.py
tests/test_unit.py
venv/bin/jp.py
crdb_dump-0.3.0.dist-info/METADATA
crdb_dump-0.3.0.dist-info/WHEEL
crdb_dump-0.3.0.dist-info/entry_points.txt
crdb_dump-0.3.0.dist-info/top_level.txt
crdb_dump-0.3.0.dist-info/RECORD
