Metadata-Version: 2.4
Name: crdb-dump
Version: 0.3.0
Summary: A CLI tool to export and import schema definitions and data from CockroachDB in SQL, JSON, YAML, or chunked CSV formats.
Author-email: Virag Tripathi <virag.tripathi@gmail.com>
License-Expression: MIT
Classifier: Development Status :: 4 - Beta
Classifier: Intended Audience :: Developers
Classifier: Topic :: Software Development :: Quality Assurance
Classifier: Programming Language :: Python :: 3
Classifier: Programming Language :: Python :: 3.7
Classifier: Programming Language :: Python :: 3.8
Classifier: Programming Language :: Python :: 3.9
Classifier: Programming Language :: Python :: 3.10
Classifier: Operating System :: OS Independent
Requires-Python: >=3.7
License-File: LICENSE
Requires-Dist: sqlalchemy
Requires-Dist: sqlalchemy-cockroachdb
Requires-Dist: click
Requires-Dist: pyyaml
Requires-Dist: psycopg2-binary
Requires-Dist: boto3
Dynamic: license-file
